{"0": ["https://batdongsan.vn/gia-chao-moi-6-ty-khu-vip-linh-trung-mtkd-10m-via-he-vo-van-ngan-xa-lo-ha-noi-80m2-2-tang-6-ty-lh-0905238089-r272310", "GIÁ CHÀO MỚI 6 TỶ KHU VIP LINH TRUNG - MTKD 10M VỈA HÈ- VÕ VĂN NGÂN- XA LỘ HÀ NỘI- 80M2 - 2 TẦNG- 6 TỶ- LH 0905238089", "NGÀY 14/7 / 2023 GIẢM SẬP SÀN 1 TỶ - GIÁ CHÀO MỚI 6 TỶ KHU VIP LINH TRUNG - MTKD 10M VỈA HÈ- VÕ VĂN NGÂN- XA LỘ HÀ NỘI- 80M2 - 2 TẦNG- 6 TỶ- LH 0905238089\nMô tả\n+ Kết cấu: 1 trệt, 1 lầu , 2 phòng ngủ, 2 wc \n+ Khu sầm uất kinh doanh đa ngành nghề\n+ Khu vực an ninh, văn hóa, dân trí cao\n+ Sổ vuông vức, không lỗi phong thủy , công chứng ngay.", "Bán Nhà mặt phố", "Thủ Đức", "6000000 tỷ", ["Mã tin: 272310", "Ngày đăng: 15:44 14/07/2023"], ["Diện tích: 80 m2"]], "1": ["https://batdongsan.vn/nha-binh-thanh-le-quang-dinh-hem-4m-ngang-4-x-13-2-tang-btct-sat-mat-tien-chi-7-ty-r272301", "Nhà Bình Thạnh, Lê Quang Định, Hẽm 4m, Ngang 4 x 13, 2 Tầng BTCT, Sát Mặt Tiền, Chỉ 7 Tỷ", "Nhà Bình Thạnh, Lê Quang Định, Hẽm 4m, Ngang 4 x 13, 2 Tầng BTCT, Sát Mặt Tiền, Chỉ 7 Tỷ\nLê Quang Định, Nguyễn Văn Đậu, Lê Trực, Tăng Bạc Hổ.\nHẽm Xe Hơi Thông Suốt, Tiện ích vây quanh, gần chợ Bà Chiểu, giáp Quận 1, 3, Phú Nhuận.\nNhà Sát Mặt Tiền Đường, gồm 2 Lầu, 3 Phỏng rộng.\nSổ Hồng Và Pháp Lý Chuẩn , Công Chứng Ngay Và Luôn.\nLiên hệ em Nguyên Nhà Đất xem nhà ngay xem nhà miễn phí\nGọi ngay: 0901486189 , 0987581589", "Bán Nhà riêng", "Bình Thạnh", "7000000 tỷ", ["Mã tin: 272301", "Ngày đăng: 16:11 14/07/2023"], ["Diện tích: 49 m2", "Phòng ngủ: 4 PN", "Phòng WC: 4 WC", "Địa chỉ: Lê Quang Định, Phường 5, Quận Bình Thạnh"]], "2": ["https://batdongsan.vn/hot-mat-tien-cuc-hiem-trung-tam-tan-phu-chi-3xiu-ty-r272300", "HOT! MẶT TIỀN CỰC HIẾM – TRUNG TÂM TÂN PHÚ – CHỈ 3.XÍU TỶ.", "Lê Trọng Tấn – 32m2 – ngang gần 4m – 4 tầng – có sân thượng.\n+ Nhà 1 trệt, 2 lầu, sân thượng, giếng trời thoáng mát, ngập tràn ánh sáng.\n+ Có 3 Phòng ngủ, 1 phòng thờ, 3 WC đầy đủ công năng cho 1 gia đình 3 thế hệ.\n+ Sổ vuông A4, hoàn công đầy đủ, pháp lý chuẩn.\nAlo em Oanh có ngay MẶT TIỀN VIP TRUNG TÂM TÂN PHÚ.", "Bán Nhà riêng", "Tân Phú", "3.3 tỷ", ["Mã tin: 272300", "Ngày đăng: 16:11 14/07/2023"], ["Diện tích: 32 m2"]], "3": ["https://batdongsan.vn/hot-mat-tien-cuc-hiem-trung-tam-tan-phu-chi-3xiu-ty-r272296", "HOT! MẶT TIỀN CỰC HIẾM – TRUNG TÂM TÂN PHÚ – CHỈ 3.XÍU TỶ.", "Lê Trọng Tấn – 32m2 – ngang gần 4m – 4 tầng – có sân thượng.\n+ Nhà 1 trệt, 2 lầu, sân thượng, giếng trời thoáng mát, ngập tràn ánh sáng.\n+ Có 3 Phòng ngủ, 1 phòng thờ, 3 WC đầy đủ công năng cho 1 gia đình 3 thế hệ.\n+ Sổ vuông A4, hoàn công đầy đủ, pháp lý chuẩn.\nAlo em Oanh có ngay MẶT TIỀN VIP TRUNG TÂM TÂN PHÚ.", "Bán Nhà riêng", "Tân Phú", "3.3 tỷ", ["Mã tin: 272296", "Ngày đăng: 16:28 14/07/2023"], ["Diện tích: 32 m2"]], "4": ["https://batdongsan.vn/hiem-mat-tien-le-trong-tan-32m2-4-tang-gia-3xiu-ty-r272292", "Hiếm! Mặt tiền Lê Trọng Tấn – 32m2 – 4 tầng – giá 3.xíu tỷ.", "+ Diện tích 32m2 - ngang gần 4m.\n+ Nhà 1 trệt, 2 lầu, sân thượng, giếng trời thoáng mát, ngập tràn ánh sáng.\n+ Có 3 Phòng ngủ, 1 phòng thờ, 3 WC đầy đủ công năng cho 1 gia đình 3 thế hệ.\n+ Sổ vuông A4, hoàn công đầy đủ, pháp lý chuẩn.\nAlo em Oanh có ngay MẶT TIỀN VIP TRUNG TÂM TÂN PHÚ.", "Bán Nhà mặt phố", "Tân Phú", "3.3 tỷ", ["Mã tin: 272292", "Ngày đăng: 17:14 14/07/2023"], ["Diện tích: 32 m2"]], "5": ["https://batdongsan.vn/nha-dep-khu-4-xa-giam-gia-hem-xe-hoi-duong-truong-phuoc-phan-binh-tri-dong-binh-tan-r272291", "Nhà đẹp khu 4 xã giảm giá, hẻm xe hơi, đường Trương Phước Phan, Bình Trị Đông, Bình Tân", "Nhà đẹp khu 4 xã giảm giá, hẻm xe hơi, đường Trương Phước Phan, Bình Trị Đông, Bình Tân\n- Diện tích 36m2, 1 trệt 1 lầu mới tinh\n- Hẻm xe hơi thông\n- Khu vực ngã 4 bốn xã, sầm uất xung quanh bệnh viện Bình Tân, trường Tiểu học, THCS, BHX, ĐMX, Coop mart ..Giao thông thuận tiện đi các ngã\n- Sổ vuông A4, công nhận đủ\nGiá bán chỉ 3,5 tỷ giảm còn 3,4 tỷ\nVui lòng liên hệ Thạc sĩ Kiệt, chuyên gia nhà phố Bình Tân để xem nhà, Sdt 0907451088", "Bán Nhà mặt phố", "Bình Tân", "3.4 tỷ", ["Mã tin: 272291", "Ngày đăng: 17:34 14/07/2023"], ["Diện tích: 36 m2", "Phòng ngủ: 2 PN", "Phòng WC: 2 WC"]], "6": ["https://batdongsan.vn/tan-binh-giap-quan-10-54m2-ngan-4m-gia-4x-ty-r272290", "TÂN BÌNH GIÁP QUẬN 10 – 54M2 –  NGAN 4M GIÁ 4.X TỶ.", "+ Diện tích: 56m2 – ngang 4m.\n+ Nhà cũ tiện xây mới theo sở thích và cao tầng như hàng xóm.\n+ 1 phút tới Công Viên Lê Thị Riêng, Quận 10, Quận 3, thêm vài phút tới Trung Tâm Sài Gòn.\nAlo em Oanh có ngay NHÀ TO – VỊ TRÍ KHỎI LO – GIÁ NHƯ TRÁI NHO.", "Bán Nhà riêng", "Tân Bình", "4.6 tỷ", ["Mã tin: 272290", "Ngày đăng: 17:47 14/07/2023"], ["Diện tích: 32 m2"]], "7": ["https://batdongsan.vn/ban-nha-nguyen-hoang-quan-2-90m2-17-ty-4-tang-so-hong-no-hau-noi-that-long-lanh-r272286", "Bán Nhà Nguyễn Hoàng Quận 2, 90m2, 17 Tỷ, 4 Tầng , Sổ Hồng Nở Hậu, Nội Thất Long Lanh", "Nội Dung:\n- Nhà mới đẹp ở ngay, thuộc khu biệt thự liền kề An Phú.\n- Diện tích 90 mét vuông, sổ hồng đẹp nở hậu 5 mét dài 20 mét\n- Lề đường trước nhà rộng, dân trí xung quanh cao.\n- Kết cấu nhà 4 tầng, Có phòng khách, Bếp, Sân thượng trước, Sân phơi sau, 5 phòng ngủ lớn, 5 nhà vệ sinh to.\n- Nội thất cao cấp, đẹp long lanh.\n- Vị trí trung tâm hành chính, Giao thông vô cùng thuận lợi.\n- Xe hơi di chuyển thuận lợi trước nhà, kết nối các tuyến trung tâm với cao tốc Long Thành – Dầu Giây\n- Tiện ích xung quanh không thiếu thứ gì, đặt biệt rất gần với siêu thị MeGa Song Hành.\n- Giá nhỉnh 17 tỷ, có thương lượng\n……………………………………….\n- Liên hệ: 0862451379 (Nam Hải)\n- Hỗ trợ xem nhà Miễn Phí\n- Hỗ trợ vay Ngân Hàng Miễn Phí", "Bán Nhà riêng", "Quận 2", "17 tỷ", ["Mã tin: 272286", "Ngày đăng: 20:10 14/07/2023"], ["Diện tích: 90 m2", "Phòng ngủ: 5 PN", "Phòng WC: 5 WC", "Địa chỉ: Khu đô thị APAK, Q2, TP.HCM"]], "8": ["https://batdongsan.vn/chinh-chu-ngop-bank-hem-o-to-ngu-trong-nha-k300-tan-binh-90m2-11-ty-0977943598-r272283", "Chính chủ ngộp bank hẻm ô tô ngủ trong nhà K300, Tân Bình 90m2 11 tỷ 0977943598", "???? ???? Ngộp Bank, giảm mạnh 2 Tỷ, tổng giảm chào 5 Tỷ. Giá chào mới là 11 Tỷ.\n\n???????????? GẦN CHỢ HOÀNG HOA THÁM TÂN BÌNH  - CHÍNH CHỦ CHƯA QUA ĐẦU TƯ SỔ A4 - XE HƠI NGỦ TRONG NHÀ - KHÔNG LỘ GIỚI - DIỆN TÍCH LỚN 90M2.\n\nMô tả: \n+ Diện tích: 90m2 ngang 4.3m dài 21m vuông vức.\n+ Xe hơi ngủ trong nhà, hẻm thông ra Hoàng Hoa Thám.\n+ Nhà chính chủ ở lâu năm, nhà cũ tiện xây mới. \n+ Khu vực yên tĩnh, có camera an ninh, đi bộ 1 phút ra chợ Hoàng Hoa Thám, trường học đủ các cấp, siêu thị các thứ, tiện ích không thiếu thứ gì.\n+ Sổ hồng chính chủ công chứng ngay, không quy hoạch, không lộ giới.\nLH: (0977943598) Giang có zalo.", "Bán Nhà riêng", "Tân Bình", "11 tỷ", ["Mã tin: 272283", "Ngày đăng: 20:32 14/07/2023"], ["Diện tích: 90 m2"]], "9": ["https://batdongsan.vn/gap-ban-nha-rieng-go-vap-nguyen-thai-son-phuong-7-3-tang-no-hau-dt-44m2-r272282", "Gấp bán Nhà Riêng Gò Vấp, Nguyễn Thái Sơn, Phường 7, 3 Tầng, Nở Hậu, DT 44m2", "Bán Nhà Riêng Gò Vấp.\nMô tả:\n- Hẻm 3 gác thông, nhà 3 mặt thoáng.\n- Nhà cũ. Tổng 3 PN + WC, bếp, Ban công thoáng.\n- Thuận tiện chuyển sang các quận trung tâm khác.\n- Tiện ích xung quanh đầy đủ: gần bệnh viện, trường học, chợ, khu mua sắm, siêu thị....\n- Khu vực an ninh, dân trí tốt.\n- Gần ĐH Công Nghiệp 4, Vincom plaza, công viên Gia Định, hẻm thông tứ tung.\n- Gọi ngay 0935610440 (Zalo) Mr Vinh xem nhà, đất trực tiếp.\n- Bất động sản nhà phố Sài Gòn - Nhà đất giá rẻ - Gặp Chính Chủ Thương Lượng\n#batdongsannhaphosaigon", "Bán Nhà riêng", "Gò Vấp", "4.3 tỷ", ["Mã tin: 272282", "Ngày đăng: 21:12 14/07/2023"], ["Diện tích: 44 m2", "Phòng ngủ: 3 PN", "Phòng WC: 3 WC"]], "10": ["https://batdongsan.vn/hiem-50m2-3-tang-btct-tt-q10-cty-dinh-gia-doc-lap-citics-dinh-gia-hon-6-ty-ban-54-ty-tl-r272272", "HIẾM-50M2 3 TẦNG BTCT-TT Q10-CTY ĐỊNH GIÁ ĐỘC LẬP CITICS ĐỊNH GIÁ HƠN 6 TỶ-BÁN 5.4 TỶ TL", "Hẻm Lý Thái Tổ Quận 10.\nDT: 4.6m x 11m x 3 tấm (42/50m²).\nGiá: 5.4 tỷ. (thương lượng).\n????Mô tả:\n+ Kết cấu: Nhà 1 trệt + 2 lầu, 3PN - 3WC.\n+ Hẻm ba gác thông khắp ngả. Cách mặt tiền đường chỉ vài bước chân.\n+ Nhà ngay trung tâm Q10, ngay ngã 7 Lý Thái Tổ.\n+ Đầy đủ tiện ích như chợ, trường học cấp 1,2 và 3, bệnh viện, công viên, siêu thị…\n+ Sổ hồng riêng đẹp, hoàn công đầy đủ, pháp lý sạch.\n=> Phù hợp đầu tư hoặc cho thuê.", "Bán Nhà riêng", "Quận 10", "5.4 tỷ", ["Mã tin: 272272", "Ngày đăng: 14:36 13/07/2023"], ["Diện tích: 50 m2", "Phòng ngủ: 3 PN", "Phòng WC: 3 WC", "Hướng nhà: Đông-Nam", "Hướng ban công: Đông-Nam", "Địa chỉ: Quận 10, Hồ Chí Minh"]], "11": ["https://batdongsan.vn/nha-chdv-dien-bien-phu-binh-thanh-ngang-104-x-186-22-phong-sat-quan-1-nhinh-17-ty-r272262", "Nhà CHDV, Điện Biên Phủ, Bình Thạnh, Ngang 10.4 x 18.6, 22 Phòng, Sát Quận 1, Nhỉnh 17 tỷ", "Nhà CHDV, Điện Biên Phủ, Bình Thạnh, Ngang 10.4 x 18.6, 22 Phòng, Sát Quận 1, Nhỉnh 17 tỷ \nĐiện Biên Phủ, Trường Sa, Mai Thị Lựu, Phan Kế Bính, Nguyễn Bĩnh Khiêm\nBình Thạnh\n195 M2 / Ngang 10.4 X 18.6 / Dtsd 780 M2\n4 Tầng, Chdv 22 Phòng Đa Số Có Gác, Đang Cho Thuê Khoáng 85 Tr.Th,  Tự Khai Thác 165 Tr.Th.\nCăng Hộ Dịch Vụ 1 Trệt 3 Lầu, Gồm 22 Phòng Khép Kín, Đầy Đủ Nội Thất Xịn Sò\nHẽm Sạch Sẽ Thoáng, An Ninh Trật Tự, Sát Hẽm Ô Tô, Chạy 3 Phút Qua Quận 1.\nSổ Hồng Và Pháp Lý Chuẩn , Công Chứng Ngay Và Luôn.\nLiên hệ em Nguyên Nhà Đất xem nhà ngay xem nhà miễn phí\nGọi ngay: 0901486189 , 0987581589", "Bán Nhà riêng", "Bình Thạnh", "17990000 tỷ", ["Mã tin: 272262", "Ngày đăng: 15:03 13/07/2023"], ["Diện tích: 195 m2", "Phòng ngủ: 22 PN", "Phòng WC: 22 WC", "Hướng nhà: Tây", "Hướng ban công: Tây", "Địa chỉ: Điện Biên Phủ, Phường 15, Quận Bình Thạnh"]], "12": ["https://batdongsan.vn/quan-10-ngay-truong-mam-non-con-meo-vang-53-ty-r272260", "QUẬN 10 - NGAY TRƯỜNG MẦM NON CON MÈO VÀNG - 5,3 TỶ", "QUẬN 10 - NGAY TRƯỜNG MẦM NON CON MÈO VÀNG\n\n✅ Địa chỉ: Nguyễn Ngọc Lộc P14, Q10\n✅ DT: 2m8 x 10.5m ( 2 Tầng )\n✅ Kết cấu: 1 trệt 1 lầu. Gồm phòng khách, bếp, 2PN, 2WC.\n✅ Trung tâm SG, sau lưng trường Việt Úc. 1 bước ra hẻm xe tải. Hẻm đẹp dân trí cao.\n\n☎️ Gọi ngay đi xem Nhà Đẹp này 093 888 6128 Thúy Dinh ( 翠莹 ).\n⏩ Kết bạn Zalo để xem kho hàng và luôn cập nhật hàng mới nhất \n---------------------\nKHÔNG TIN ẢO - NHÀ THẬT HÌNH THẬT\nMs685", "Bán Nhà riêng", "Quận 10", "5.3 tỷ", ["Mã tin: 272260", "Ngày đăng: 15:09 13/07/2023"], ["Diện tích: 30 m2", "Phòng ngủ: 2 PN"]], "13": ["https://batdongsan.vn/nha-dep-gia-re-duong-so-14-phuong-8-go-vap-38m2-4-tang-chi-5-ty-r272252", "Nhà đẹp giá rẻ Đường số 14 Phường 8 Gò Vấp 38m2, 4 tầng chỉ 5 tỷ", "MS 18223\n* Vị trí: Gò Vấp, đường Số 14, gần Trạm Y tế Phường 8, ngã 3 Quang Trung-Tân Sơn.\n* Nhà mới, đẹp, ở ngay, \n* Diện tích 38m2, nở hậu, 4 tầng gồm 2 phòng khách, phòng bếp, 3 phòng ngủ, 4 WC, phòng thờ, sân thượng sau.\n* Hẻm thông. \n* Chủ tặng full nội thất xịn xò như sopha, giường, tủ, kệ, tủ bếp, máy lạnh....cho khách mua thiện chí.", "Bán Nhà riêng", "Gò Vấp", "5 tỷ", ["Mã tin: 272252", "Ngày đăng: 15:42 13/07/2023"], ["Diện tích: 38 m2", "Phòng ngủ: 3 PN", "Phòng WC: 4 WC", "Địa chỉ: Đường Số 14"]], "14": ["https://batdongsan.vn/nha-dep-gia-re-duong-so-14-phuong-8-go-vap-38m2-4-tang-chi-5-ty-r272251", "Nhà đẹp giá rẻ Đường số 14 Phường 8 Gò Vấp 38m2, 4 tầng chỉ 5 tỷ", "MS 18223\n* Vị trí: Gò Vấp, đường Số 14, gần Trạm Y tế Phường 8, ngã 3 Quang Trung-Tân Sơn.\n* Nhà mới, đẹp, ở ngay, \n* Diện tích 38m2, nở hậu, 4 tầng gồm 2 phòng khách, phòng bếp, 3 phòng ngủ, 4 WC, phòng thờ, sân thượng sau.\n* Hẻm thông. \n* Chủ tặng full nội thất xịn xò như sopha, giường, tủ, kệ, tủ bếp, máy lạnh....cho khách mua thiện chí.", "Bán Nhà riêng", "Gò Vấp", "5 tỷ", ["Mã tin: 272251", "Ngày đăng: 15:42 13/07/2023"], ["Diện tích: 38 m2", "Phòng ngủ: 3 PN", "Phòng WC: 4 WC", "Địa chỉ: Đường Số 14"]], "15": ["https://batdongsan.vn/ban-nha-20154a-ma-lo-xe-hoi-vao-nha-gan-cho-dien-tich-4x13m-khong-lo-gioi-r272245", "Bán nhà 201/5/4A Mã Lò-xe hơi vào nhà- gần chợ, diện tích 4x13m, không lộ giới", "Bán nhà Mã Lò-xe hơi vào nhà- gần chợ, diện tích 4x13m, không lộ giới\n+ Kết cấu: gác lửng, 2 PN, 2 WC. \n+ Vị trí: hẻm 5,4m Mã Lò, gần chợ, trường học, siêu thị, gần BV Bình Tân, siêu thị, trường học\n+ Sổ vuông, đẹp, mua bán nhanh, nhà cao ráo, mát mẻ, đang cho thuê.\n+ DT: 51,2m2, DTSD: 68m2. Giá tốt: 4.5tỷ (thương lượng).\n\nVị trí nhà ở Mã Lò nằm ở ngay vị trí giao thông đắt giá, thuận tiện di chuyển đến các quận trung tâm của thành phố như Quận 11, Quận 6, Quận 10. Ngoài ra từ Mã Lò cũng dễ dàng di chuyển đến các khu công nghiệp, khu chế xuất, sân bay Tân Sơn Nhất.\nĐiện thoại: 0903647456 (chính chủ - Thu)", "Bán Nhà riêng", "Bình Tân", "4.4 tỷ", ["Mã tin: 272245", "Ngày đăng: 16:10 13/07/2023"], ["Diện tích: 68 m2", "Phòng ngủ: 2 PN", "Phòng WC: 2 WC", "Hướng nhà: Nam", "Địa chỉ: 201/5/4A Mã Lò, P Bình Hưng Hòa, Bình Tân"]], "16": ["https://batdongsan.vn/ban-mat-tien-kinh-doanh-nga-3-cho-khieu-nang-tinh-giap-quan-6-r272243", "BÁN MẶT TIỀN KINH DOANH NGÃ 3 CHỢ KHIẾU NĂNG TĨNH - GIÁP QUẬN 6", "MẶT TIỀN KINH DOANH NGÃ 3 CHỢ KHIẾU NĂNG TĨNH - GIÁP QUẬN 6 KẾ BÊN KHU TÊN LỬA AEON MALL BÌNH TÂN - NHÀ MỚI 2 TẦNG NHỈNH 5 TỶ. \nNHÀ ĐANG CHO THUÊ LÀM SPA 11 TRIỆU/THÁNG. \n+ Diện tích: 4 × 11m \n+ Đường 6m thông tứ tung. \n+ Kết cấu: Nhà 2 tầng trệt lầu gồm 2PN 2 VS. \n+ Vị trí: Mặt tiền Kinh doanh ngay chợ Khiếu Năng Tĩnh, Giáp Q6 gần khu Tên Lửa. Gần các trục đường chính Khiếu Năng Tĩnh, Đường số 7, Tỉnh Lộ 10, An Dương Vương...vt7 \n+ Công năng: Gia đình ở, Kinh doanh đỉnh.\n + Sổ hồng hoàn công đầy đủ công chứng ngay", "Bán Nhà mặt phố", "Bình Tân", "5700000000 tỷ", ["Mã tin: 272243", "Ngày đăng: 16:15 13/07/2023"], ["Diện tích: 44 m2", "Phòng ngủ: 2 PN", "Phòng WC: 2 WC"]], "17": ["https://batdongsan.vn/hem-oto-1truc-49m2-5-tang-go-vap-nha-moi-tang-toan-bo-noi-that-r272234", "HẺM ÔTÔ 1TRỤC - 49M2 - 5 TẦNG - GÒ VẤP NHÀ MỚI - TẶNG TOÀN BỘ NỘI THẤT", "+ Cách MT Phạm Văn Chiêu tầm 100m, hẻm thẳng 1 trục xe hơi tới nhà, rất tiện làm văn phòng Công ty hoặc kinh doanh buôn bán nhỏ.\n+ Kết cấu: Trệt, lửng, 3 lầu, 5 Phòng ngủ, 1 Phòng thờ, 5WC, có sân thượng sau.\n+ Nhà mới ở ngay chủ tặng toàn bộ nội thất bên trong.\n+ Nhà trống, khóa số anh chị em dẫn khách ngày đêm luôn ạ.\n4825.413 62", "Bán Nhà riêng", "Gò Vấp", "6.2 tỷ", ["Mã tin: 272234", "Ngày đăng: 17:14 13/07/2023"], ["Diện tích: 49 m2", "Phòng ngủ: 5 PN", "Phòng WC: 5 WC", "Địa chỉ: phạm văn chiêu"]], "18": ["https://batdongsan.vn/lac-long-quan-48m2-ngang-hon-6-m-2-tang-gia-nhinh-5-ty-r272233", "Lạc Long Quân – 48m2 – ngang hơn 6 m - 2 tầng – giá nhỉnh 5 tỷ.", "+ Diện tích: 6m x 8m.\n+ Sổ đẹp, hoàn công đủ, pháp lý chuẩn.\n+ Nhà mới đẹp gồm: trệt, lầu, 2 phòng ngủ, 2WC, phòng khách, phòng bếp.\n+ Trước nhà có khoảng sân 15m, để được đến 7 chiếc xe máy, tha hồ tụ tập ngày cuối tuần bên người thân, bạn bè.\nAlo em Oanh có ngay NHÀ ĐẸP – NƠI TỤ HỌP CUỐI TUẦN VUI VẺ VỚI NGƯỜI THÂN YÊU.", "Bán Nhà riêng", "Tân Bình", "5.3 tỷ", ["Mã tin: 272233", "Ngày đăng: 17:20 13/07/2023"], []], "19": ["https://batdongsan.vn/nha-moi-dep-ngang-hon-6m-phuong-10-trung-tam-gia-5x-ty-r272228", "NHÀ MỚI ĐẸP - NGANG HƠN 6M - PHƯỜNG 10 TRUNG TÂM – GIÁ 5.X TỶ.", "+ Diện tích: 6m x 8m.\n+ Sổ đẹp, hoàn công đủ, pháp lý chuẩn.\n+ Nhà mới đẹp gồm: trệt, lầu, 2 phòng ngủ, 2WC, phòng khách, phòng bếp.\n+ Trước nhà có khoảng sân 15m, để được đến 7 chiếc xe máy, tha hồ tụ tập ngày cuối tuần bên người thân, bạn bè.\nAlo em Oanh có ngay NHÀ ĐẸP – NƠI TỤ HỌP CUỐI TUẦN VUI VẺ VỚI NGƯỜI THÂN YÊU.", "Bán Nhà riêng", "Tân Bình", "5.3 tỷ", ["Mã tin: 272228", "Ngày đăng: 18:10 13/07/2023"], []]}