{"0": ["https://batdongsan.vn/ban-nha-dep-o-ngay-quan-10-ngang-4m7-2-tang-btct-hem-cach-nha-xe-hoi-chi-3-ty-5-r271330", "Bán Nhà Đẹp ở Ngay Quận 10, ngang 4m7, 2 tầng BTCT, Hẻm Cách Nhà Xe Hơi, Chỉ 3 tỷ 5.", "???? Quận 10 Sát Mặt Tiền, Ngang hoa khôi 4,7m 32/44m2 - 2 Tầng BTCT 2 PN. ????  Không Lộ Giới – Không Quy Hoạch????\n???? Bán nhà mới ở ngay đẹp lung linh đường Trần Nhân Tôn, Phường 2, Quận 10, gia chủ tặng toàn bộ nội thất sang chảnh cho người hữu duyên. Ưu tiên khách  mua ở\n+ Diện tích: 32m2 công nhận/43m2 đất sử dụng (ngang 4m7 nở hậu 4m9, dài 10m)\n+ Vị trí trung tâm Sài Gòn, duy chuyển Quận 5, Quận 3, Quận 1 hơn 5 phút, hẻm thông tứ tung.\n+ Hiện trạng nhà 2 Tầng BTCT.\n???? Giá 3 tỷ 500 còn thương lượng.\nLiên hệ xem nhà 0938509958", "Bán Nhà riêng", "Quận 10", "Thỏa thuận", ["Mã tin: 271330", "Ngày đăng: 00:01 05/07/2023"], []], "1": ["https://batdongsan.vn/go-vap-duong-so-51-phuong-14-66m2-4x165-3-tang-chi-545-ty-r271326", "Gò Vấp Đường Số 51 Phường 14, 66m2, 4x16.5, 3 tầng chỉ 5.45 tỷ", "MS 17223\n* Vi trí: nhà hẻm đường Số 51 Phường 14 Gò Vấp\n* Diện tích 66m2, ngang 4m, dài 16.5m, 3 tầng với 4 phòng ngủ, 3 WC.\n* Hẻm ba gác, cách hẻm xe hơi 30m. Hẻm yên tĩnh, hàng xóm thân thiện.\n* Sổ hồng, công chứng ngay.", "Bán Nhà riêng", "Gò Vấp", "5.45 tỷ", ["Mã tin: 271326", "Ngày đăng: 08:22 05/07/2023"], ["Diện tích: 66 m2", "Phòng ngủ: 4 PN", "Phòng WC: 3 WC", "Địa chỉ: Đường Số 51"]], "2": ["https://batdongsan.vn/nha-moi-khu-phan-lo-dso-59-phuong-14-go-vap-45m2-5-tang-chi-76-ty-r271321", "Nhà mới, khu phân lô Đ.Số 59 Phường 14 Gò Vấp, 45m2, 5 tầng chỉ 7.6 tỷ", "MS 17323\n* Vị trí: đường Số 59 Phường 14 Gò Vấp. Khu phân lô đồng bộ.\n• Nhà mới, nội thất cao cấp, đầy đủ, chủ mới dọn đồ vô ở ngay.\n• Đường trước nhà tráng nhựa rộng 6.5m, lề 3m, rộng rãi, thông thoáng. Khu vực an ninh yên tĩnh.\n* Diện tích 45m2, 5 tầng BTCT kiên cố, gồm Trệt, lửng, 3 lầu với 3 phòng ngủ, 4WC.\n* Pháp lý chuẩn, công chứng giao nhà ngay.", "Bán Nhà riêng", "Gò Vấp", "7.6 tỷ", ["Mã tin: 271321", "Ngày đăng: 08:57 05/07/2023"], ["Diện tích: 45 m2", "Phòng ngủ: 3 PN", "Phòng WC: 4 WC", "Địa chỉ: Đường Số 59"]], "3": ["https://batdongsan.vn/bui-van-ha-r271312", "Bùi Văn Hà", "Cần bán gấp căn nhà  96m2 ở đường Bùi Thanh Khiết , bình chánh, hcm.\nDiện tích: 4x 24, Xe ???? tới nhà\n-Chỉ Cần 426tr là có thể sở hữu(Ngân Hàng Hỗ Trợ 70%)\n-Thiết kế: 1 sân trước+ sân sau, 1 phòng khách, 2 phòng ngủ, 2 toilet, 1 nhà ăn + bếp + 1 ban công. Nhà xây dựng kiên cố, mâm đúc chắc\n-Đường trước nhà 6m bao oto quay đầu\n-Vị trí: Đường Bùi Thanh Khiết Bình Chánh,  Nhà rất đẹp gần các tụ điểm như trường học, trạm y tế, ủy ban, bách hoá xanh cách chợ bình chánh 860m...\nPháp lý: Sổ hồng riêng, đảm bảo về mặc pháp lý.\nGiá: 1tỷ326 sổ hồng riêng( Bao tên công chứng).\nLH:  0373882260 (Em Hà)", "Bán Nhà mặt phố", "Bình Chánh", "480 tỷ", ["Mã tin: 271312", "Ngày đăng: 09:35 05/07/2023"], ["Diện tích: 96 m2", "Phòng ngủ: 2 PN", "Phòng WC: 2 WC", "Hướng nhà: Đông-Nam", "Hướng ban công: Đông-Nam", "Địa chỉ: đường bùi thanh khiết , xã bình chánh , huyện bình chánh, tp.hcm, Bùi Thanh Khiết"]], "4": ["https://batdongsan.vn/nha-duong-so-3-f9-go-vap-hem-oto-4165m-2-lau-san-thuong-r271308", "NHÀ ĐƯỜNG SỐ 3 F9 GÒ VẤP. HẺM OTO 4×16,5M, 2 LẦU, SÂN THƯỢNG", "NHÀ BÁN CHÍNH CHỦ\nGia đình tôi cần bán gấp căn nhà tọa lạc tại đường số 3 F9 Gò Vấp, nhà hẻm oto cụt, khu dân cư văn minh, lịch sự sạch sẽ, an ninh.\nNhà được xây dựng trên nền đất vuông vứt, không tóp hậu. Xây mới và sổ hồng hoàn công tháng 8/2022\n???? DT: 4×16,5m. Trệt, 2 lầu, sân thượng, 4pn, 4wc, sân để xe rộng rãi, nội thất cao cấp\n???? Giá bán: 5ty9 thương lượng chút ít cho người thiện chí.\n???? XIN MIỄN TRUNG GIAN, QUẢNG CÁO.", "Bán Nhà", "Gò Vấp", "5.9 tỷ", ["Mã tin: 271308", "Ngày đăng: 09:47 05/07/2023"], ["Diện tích: 66 m2", "Phòng ngủ: 4 PN", "Phòng WC: 4 WC", "Hướng nhà: Tây-Nam", "Hướng ban công: Tây-Nam", "Địa chỉ: Đường số 3 F9 Gò Vấp"]], "5": ["https://batdongsan.vn/nha-biet-thu-vuon-diuy-nhat-1-can-co-so-125m2-r271301", "Nhà biệt thự vườn diuy nhất 1 căn CÓ SỔ 125m2", "Nhà biệt thự siêu hot ở Tỉnh Lộ 10 Bính Chánh\nGiá 750tr\n✅ DT : 5m x 25m, thổ cư 100%\n✅ Biệt thự xây dựng 1 trệt 1 lầu, 1 PK lớn, 1 bếp, 1 phòng ăn, 3 PN, 3 WC, 1 phòng thờ, 1 phòng đọc sách, ban công, sân trước, sân vườn sau nhà.\n✅ Xung quanh tiện ích đa dạng - đầy đủ: chợ, ubnd, bhx, Trường học, bệnh viện, 3 cụm kcn lớn... => Đảm bảo cho khách hàng an cư - lập nghiệp lâu dài.\n✅ Cách Bính Chánh TP HCM 10ph di chuyển\n Pháp lý : sổ hồng trao tay.\n\nGọi ngay để được tư vấn : 0372870144 Ngọc My", "Bán Nhà riêng", "Bình Chánh", "750 triệu", ["Mã tin: 271301", "Ngày đăng: 10:54 05/07/2023"], ["Diện tích: 125 m2", "Phòng ngủ: 3 PN", "Phòng WC: 3 WC"]], "6": ["https://batdongsan.vn/nha-hem-188631-duong-htp-kp6-thi-tran-nha-be-198-ty-dt-3m-x-9m-gom-1-tret-2-lau-r271299", "NHÀ HẺM 1886/31 ĐƯỜNG HTP .......... KP6 _THỊ TRẤN NHÀ BÈ......... 1,98 tỷ DT : 3m x 9m - gồm 1 trệt 2 lầu", "Sân thượng trước VÀ 3 PN lớn - 4WC\nNhà nằm ngay mặt tiền chính 6m nên thuận tiện cho việc kinh doanh,,buôn bán mọi nghành nghề.\n_Đất thổ cư 100% - có giấy phép xây dựng\n_ Pháp lý : Sổ hồng chung - Mua bán công chứng uỷ quyền 1 phần - giao sổ hồng chính.\n...... Giá : 1 TỶ 980tr còn thương lượng....\nKhách hàng có nhu cầu mời liên hệ sđt ; 0399684188", "Bán Nhà riêng", "Nhà Bè", "1.98 tỷ", ["Mã tin: 271299", "Ngày đăng: 11:06 05/07/2023"], ["Diện tích: 27 m2", "Địa chỉ: KP6-TT NHÀ BÈ"]], "7": ["https://batdongsan.vn/can-ban-nha-4-tang-mat-tien-duong-vo-van-ngan-p-linh-chieu-dien-tich-240m-gia-498-ty-r271297", "Cần bán Nhà 4 Tầng Mặt tiền đường Võ Văn Ngân, P. Linh Chiểu, Diện tích 240m², Giá 49.8 Tỷ", "Cần bán Nhà 4 Tầng Mặt tiền đường Võ Văn Ngân, P. Linh Chiểu, Diện tích 240m², Giá 49.8 Tỷ\n+ Diện tích 240 m², (4,7mx51,72m), Sổ CN 213,8 m²,  ( 4,7mx46,29m)\n+ Diện tích sàn 373,3 m², Hướng Tây Nam, vỉa hè 5m để xe rất thoái mái. Phong thuỷ tốt, chủ ăn nên làm ra.\n+ Giá bán : 49 Tỷ 800 triệu ( thương lượng )\n\n+ Kết cấu nhà 4 tầng BTCT. gồm 10 phòng, có thể thiết kế thêm thang máy để lên tầng thượng. Khu vực được phép xây cao 7 tầng.\n+ Nhà đang cho thuê kinh doanh giá 70 triệu/tháng trong mùa dịch đén nay. Nếu cải tạo chút ít dư sức cho thuê trên 100 triệu/tháng.\n+ Sổ đẹp hoàn công, vuông vức, pháp lý chuẩn, công chứng nhanh.\n\n- Vị trí nhà nằm trên con đường đắt đỏ nhất nhì Phường TP Thủ Đức, kết nối với các tuyền đường lớn như Đặng Văn Bi, Kha Vạn Cân, Phạm Văn Đồng, Tô Vĩnh Diện, Lê Văn Chí.. Sát Ngã 4 Thủ Đức , Siêu thị Nguyễn Kim  - đường Lê Văn Việt và chợ Thủ Đức , - Khu vực kinh doanh cực kỳ sầm uất, toàn cao ốc, trụ sở văn phòng công ty, đường 2 chiều lại có vỉa hè đậu đổ Ô tô thoải mái, phù hợp kinh doanh mọi ngành nghề.\nLiên hệ : 0898 408 677 xem nhà, làm việc chính chủ", "Bán Nhà mặt phố", "Thủ Đức", "49.8 tỷ", ["Mã tin: 271297", "Ngày đăng: 11:28 05/07/2023"], ["Diện tích: 240 m2", "Địa chỉ: Đường Võ Văn Ngân, Phường Linh Chiểu, Quận Thủ Đức, TP HCM"]], "8": ["https://batdongsan.vn/ban-nha-le-van-quoi-binh-tan-40m2-2-tang-btct-2pn-kinh-doanh-dinh-chi-nhinh-4-ty-tl-r271296", "Bán nhà Lê Văn Quới Bình Tân 40m2, 2 tầng BTCT, 2PN, Kinh Doanh Đỉnh, chỉ nhỉnh 4 tỷ TL", "HẺM NHƯ MẶT TIỀN - THÔNG TỨ TUNG - Ô TÔ CHẠY VI VU\n\n+ Nhà đang cho thuê giá hổ trợ 7 triệu/ tháng. \n\n+ Diện tích 4 X 10m.\n\n+ Kết cấu 1 trệt 1 lầu, 2 phòng ngủ. \n \n+ Hẻm 8m thông, cực đẹp, sạch sẽ, khu vực an ninh, dân cư đông đúc, văn minh. \n\n+ Nhà tiện vừa ở vừa kinh doanh, hoặc cho thuê kinh doanh.\n\n+ Vị trí gần tiếp giáp với Q.Tân Phú, gần khu vực trung tâm.\n\n+ Sổ đẹp hoàn công đủ.\n\n+ Giá thỏa thuận.\n\n+ LH Nguyễn Tiền xem nhà, thương lượng giá cả làm việc chính chủ.", "Bán Nhà mặt phố", "Bình Tân", "4.1 tỷ", ["Mã tin: 271296", "Ngày đăng: 15:40 04/07/2023"], ["Diện tích: 40 m2", "Phòng ngủ: 2 PN", "Phòng WC: 2 WC", "Địa chỉ: đường lê văn quới, bình trị đông, bình tân"]], "9": ["https://batdongsan.vn/nha-2-tam-duong-32-linh-dong-thu-duc-4128-xe-hoi-dau-truoc-cua-r271293", "Nhà 2 tấm đường 32, Linh Đông, Thủ Đức, 4*12.8, xe hơi đậu trước cửa", "Nhà 2 tấm đường 32, Linh Đông, Thủ Đức, 4*12.8, xe hơi đậu trước cửa.\n\nChủ cần bán nhanh giảm giá chào ngày giá chào mới 4 tỷ 2\n\nTiện ích: \n+ Nhà BTCT chắc chắn, 1 lầu, 1 trệt, phòng khách, bếp, 2 phòng ngủ, 2 wc, sân trước, ô giếng trời phía sau.\n+ Khu dân cư yên tĩnh, an Ninh tốt, hàng xóm thân thiện, sát bên cạnh chung cư 4S Linh Đông, 300m ra Phạm Văn Đồng 1km chợ Hiệp Bình, Gigamail, trường học....\n+ Nhà mới xây rất mới chỉ việc xách vali vào ở ngay\n+ Sổ hồng chính chủ, hoàn công đầy đủ, sẵn sàng công chứng ngay trong ngày", "Bán Nhà riêng", "Thủ Đức", "4.2 tỷ", ["Mã tin: 271293", "Ngày đăng: 15:33 04/07/2023"], ["Diện tích: 52 m2", "Phòng ngủ: 3 PN", "Phòng WC: 3 WC", "Địa chỉ: Thủ Đức"]], "10": ["https://batdongsan.vn/ban-nha-phan-huy-ich-phuong-14-go-vap-77m2-hem-8m-gia-11x-ti-tl-r271283", "Bán nhà Phan Huy Ích, Phường 14, Gò Vấp, 77m2, Hẻm 8m, Giá 11,x tỉ TL", "Phan Huy Ích - P.14 - Gò Vấp - HCM \nHướng: Đông \nKết cấu: 1 trệt 1 lửng 3 lầu gồm sân xe máy gara xe hơi phòng khách bếp 4 pn 5 toilet 1 phòng xông hơi spa chăm sóc sức khoẻ phòng thờ phòng giặt sân thượng trước & sau.\nĐường: 8m thông bàn cờ\nDiện tích: Ngang 4.5m x dài 17m\nTiện ích xung quanh đầy đủ\nPháp lý: Sổ hồng riêng\nNội thất bàn giao: Full option nhà thiết kế có thang máy 450kg.", "Bán Nhà riêng", "Gò Vấp", "115 tỷ", ["Mã tin: 271283", "Ngày đăng: 10:44 04/07/2023"], ["Diện tích: 77 m2", "Phòng WC: 5 WC", "Địa chỉ: Hồ Chí Minh"]], "11": ["https://batdongsan.vn/mat-tien-kinh-doanh-khu-sam-uat-ngay-nga-3-nguyen-van-dau-lo-goc-2-mat-thoang-54m2-gia-nhinh-4-ty-r271278", "MẶT TIỀN KINH DOANH KHU SẦM UẤT - NGAY NGÃ 3 NGUYỄN VĂN ĐẬU - LÔ GÓC 2 MẶT THOÁNG - 54M2 - GIÁ NHỈNH 4 TỶ", "- MT TRẦN BÌNH TRỌNG diện tích 4.5 x 12m- Phường 5 Bình Thạnh\n- Mặt tiền kinh doanh khu sầm uất, đang kinh doanh quán cf, trước cho thuê được 20tr/tháng.\n- Tiện ích xung quanh đầyđủ\n- Giá NHỈNH 4 TỶ", "Bán Nhà mặt phố", "Bình Thạnh", "4 tỷ", ["Mã tin: 271278", "Ngày đăng: 11:23 04/07/2023"], ["Diện tích: 54 m2", "Phòng WC: 3 WC", "Địa chỉ: Hồ Chí Minh"]], "12": ["https://batdongsan.vn/ban-nha-mat-tien-quan-4-duong-so-vinh-hoi-nha-5-tang-kdc-hien-huu-101m2-san-gia-chi-nhinh-5-ty-r271271", "Bán nhà mặt tiền quận 4 - đường số Vĩnh Hội - nhà 5 tầng kdc hiện hữu 101m2 sàn giá chỉ nhỉnh 5 tỷ", "NHÀ MẶT TIỀN QUẬN 4 - ĐƯỜNG SỐ VĨNH HỘI PHƯỜNG 4 RỘNG 6M XE HƠI TRÁNH NHAU VÔ TƯ - NHÀ 5 TẦNG HOÀN CÔNG ĐỦ 101M2 - GIÁ CHỈ NHỈNH 5 TỶ.\nMô tả: \nDiện tích: 21.2m2 (3.1 x 7.2), diện tích sàn 101m2. Nhà hướng Đông Nam.\nKết cấu: nhà 5 tầng gồm 1 trệt + lửng + 2 lầu + sân thượng. Có 3 phòng ngủ, 3 toilet, phòng khách, bếp ăn rộng rãi, sân thượng thoáng mát.\nVị trí: nhà mặt tiền đường số Vĩnh Hội rộng 6m xe hơi tránh nhau thoải mái, xe hơi đỗ trước nhà. Cách vòng xoay Tân Vĩnh vs Vĩnh Hội 200m, cách cầu Ông Lãnh 700m, di chuyển qua trung tâm quận 1 chỉ 3 phút chạy xe máy.\nTiện ích: nhà mặt tiền đường khu dân cư hiện hữu chỉnh trang, khu kinh doanh mua bán sầm uất. Nhà có mặt bằng vừa ở vừa kinh doanh đa ngành nghề. Nhà gần chợ, siêu thị, quán ăn uống, cửa hàng buôn bán đầy đủ. Nhà gần hồ bơi Vân Đồn, gần trung tâm thể dục thể thao, gần trường học, bệnh viện quận 4.\nPháp lý: sổ hồng riêng chính chủ, hoàn công đủ. Đất kdc hiện hữu chỉnh trang, không quy hoạch. Sổ sẵn công chứng mua bán ngay.\nGiá chủ bán nhỉnh hơn 5 tỷ còn thương lượng.\nLiên hệ khoaland xem nhà.", "Bán Nhà mặt phố", "Quận 4", "Thỏa thuận", ["Mã tin: 271271", "Ngày đăng: 12:07 04/07/2023"], ["Diện tích: 21 m2", "Phòng ngủ: 3 PN", "Phòng WC: 3 WC", "Hướng nhà: Đông-Nam"]], "13": ["https://batdongsan.vn/ban-nha-le-dinh-can-145-m2-gia-chi-58-ty-r271253", "BÁN NHÀ LÊ ĐÌNH CẨN - 145 M2 - GIÁ CHỈ 5,8 TỶ", "BÁN NHÀ LÊ ĐÌNH CẨN - 145 M2 - GIÁ CHỈ 5,8 TỶ \n\nCĂN HỘ DỊCH VỤ 15 PHÒNG CHO THUÊ - NGANG 8 ĐỒ SỘ - CÁCH MẶT TIỀN 3 BƯỚC CHÂN - CHỈ 45TR/M2 CẢ NHÀ. \n\n+ Hiện trạng nhà gồm 2 căn, Chủ nhà bán 2 căn, không bán 1 căn. \n\n- Căn thứ nhất thiết kế 1 trệt 2 lầu đúc BTCT chắc chắn. \n- Căn thứ hai thiết kế 1 trệt 1 lầu đúc. \n\n+ Tổng cộng có 15 phòng đang cho thuê, thu nhập trung bình gần 30tr/tháng. \n\n+ Phù hợp cho Khách hàng có nhu cầu mua cho thuê dài hạn. Khách mua về có thể sửa sang lại Phòng hiện đại hơn, giá trị cho thuê sẽ tăng cao hơn nữa. \n\n+ Cách mặt tiền chỉ 3 bước chân. Giá quá bèo. \n\n+ Sổ hồng chính chủ,hoàn công,công chứng ngay", "Bán Nhà mặt phố", "Bình Tân", "5800000000 tỷ", ["Mã tin: 271253", "Ngày đăng: 14:51 04/07/2023"], ["Diện tích: 145 m2", "Phòng ngủ: 15 PN", "Phòng WC: 15 WC"]], "14": ["https://batdongsan.vn/ban-nha-1tret-2lau-tum-duong-so-8-hiep-binh-phuoc-thu-duc-gia-6-ty-r271249", "Bán nhà 1Trệt 2lầu tum, đường số 8 Hiệp Bình Phước Thủ Đức, Giá 6 Tỷ", "Bán nhà 1Trệt 2lầu tum, đường số 8 Hiệp Bình Phước Thủ Đức, Giá 6 Tỷ\t\nĐường số 8. Ngay Phở Huỳnh Trâm ( QL 13 ) đi vào nhà 200m \n- Diện tích : 56m2 4m x 14m.\n- Giá bán : 6 tỷ tl.\n- Tổng Diên tích xd : 220m² \n- Nhà 1 trệt 2 lầu + tum + Sân thượng trước sau. Có 4 phòng ngủ, 5WC, p. Khách, bếp, p. Thờ\n- Nhà cách Quốc Lộ 13 chỉ 200m, đường nhựa 5m thông qua khu dâ cư Hồng Long dễ dàng di chuyển. \n- Đi quốc lộ 13 hay ra phạm văn đồng đi các hướng vào trung tâm thành phố hoặc đi bình dương đều dễ dàng.\n- Khu nhà đồng bộ, dân cư đông, an ninh và không bị ngập nước.\n- Nội thất nhà cơ bản có sẵn tủ rèm.\nLiên hệ : 0898 408 677 xem nhà, làm việc chính chủ", "Bán Nhà", "Thủ Đức", "6 tỷ", ["Mã tin: 271249", "Ngày đăng: 14:56 04/07/2023"], ["Diện tích: 56 m2", "Phòng ngủ: 4 PN", "Phòng WC: 5 WC", "Địa chỉ: Đường Số 8, Phường Hiệp Bình Phước, Quận Thủ Đức, TP HCM"]], "15": ["https://batdongsan.vn/hem-xe-hoi-d-cua-43m2-nha-dep-1tret-3lau-gan-duong-vi-tri-dep-7xty-r271248", "HẺM XE HƠI ĐỖ CỬA - 43M2 - NHÀ ĐẸP 1TRỆT 3LẦU - GẦN ĐƯỜNG - VỊ TRÍ ĐẸP - 7.xTỶ", "Lê Văn Duyệt ,Phường 3 ,Bình Thạnh \n- Hẻm ô tô đỗ cửa, vị trí đẹp\n- Nhà thiết kế theo phong cách Châu Âu, 1 trệt, 3 lầu: Tổng 4PN + WC, bếp, phòng khách, phòng làm việc, phòng thờ, sân thượng trước sau.\n- Thuận tiện đi lại các Quận trung tâm khác.\n- Khu vực dân trí tốt, an ninh.\n- Tiện ích xung quanh đầy đủ: gần trường học các cấp, chợ, bệnh viện, siêu thị...", "Bán Nhà riêng", "Bình Thạnh", "9.7 tỷ", ["Mã tin: 271248", "Ngày đăng: 18:29 24/06/2023"], ["Diện tích: 43 m2", "Phòng ngủ: 4 PN", "Phòng WC: 4 WC", "Địa chỉ: lê văn duyệt"]], "16": ["https://batdongsan.vn/ban-gap-ong-ich-khiem-p5-q11-44m2-2-tang-dep-o-ngay-chi-49-ty-0354095924-r271243", "BÁN GẤP ÔNG ÍCH KHIÊM, P5, Q11 44M2, 2 TẦNG ĐẸP Ở NGAY, CHỈ 4.9 TỶ, 0354095924", "Chủ nhà cần bán gấp cho ai thiện chí mua \nLH: 0354095924\n\n- DT: 44m2 công nhận đủ, hẻm thông thoáng cách HXH 2 căn \n\n- Kết cấu: 2 tầng BTCT, Có 2pn, \n\n- Pháp lý rõ ràng, có thể xem nhà công chứng ngay.\n\n- Giá chỉ 4.9 TỶ thương lượng.\n\nGỌI NGAY: 0354095924(Quỳnh Nhi) nghe máy 24/24.", "Bán Nhà riêng", "Quận 11", "4.9 tỷ", ["Mã tin: 271243", "Ngày đăng: 15:26 01/07/2023"], ["Diện tích: 44 m2", "Địa chỉ: ÔNG ÍCH KHIÊM, PHƯỜNG 5, QUẬN 11"]], "17": ["https://batdongsan.vn/ban-nha-hem-xe-tai-6m-khu-phan-lo-sat-mat-tien-duong-hiep-binh-thu-duc-100m-70-m2-4-tang-4pn-chi-nhinh-6-ty-r271235", "Bán nhà hẻm xe tải 6m, khu phân lô, sát mặt tiền đường Hiệp Bình Thủ Đức 100m, 70 m2, 4 tầng, 4pn, chỉ nhỉnh 6 tỷ.", "Bán nhà hẻm xe tải 6m, khu phân lô, sát mặt tiền đường Hiệp Bình Thủ Đức 100m, 70 m2, 4 tầng, 4pn, chỉ nhỉnh 6 tỷ.\n+ Diện tích: 70m2( 4× 17.5m) \n+ Kết cấu: 1 trệt, 2 lầu, sân thượng thông thoáng,4pn, 5wc, ban công\n+ Cách 200m ra mặt tiền đường Hiệp Bình, khu tập trung dân cư đông đúc, gần chợ Hiệp Bình, Trường , Bách hóa xanh, Trường tiểu học...\n+ Pháp lý chuẩn chỉnh, hoàn công đầy đủ.\n+ Giá chào: 6 tỷ 3 ( thương lượng) \n☎️ 0905238089 Mr Ảnh Nguồn nhà tốt.", "Bán Nhà mặt phố", "Thủ Đức", "6300000 tỷ", ["Mã tin: 271235", "Ngày đăng: 16:44 01/07/2023"], ["Diện tích: 70 m2"]], "18": ["https://batdongsan.vn/nha-mat-tien-bau-cat-1-kien-co-4-tang-tien-o-kinh-doanh-chi-12-ty-r271234", "Nhà mặt tiền Bàu Cát 1, kiên cố 4 tầng tiện ở, kinh doanh, chỉ 12 tỷ", "Mặt tiền kinh doanh Bàu Cát 1. Xây kiên cố 4 tầng, nhà có 4 phòng ngủ chính, 4WC. Sân thượng, giếng trời, ban công từng tầng. Vĩa hè trước nhà đậu được nhiều xe hơi. \n    Nhà trong khu dân trí, văn minh. Phù hợp ở vừa kinh doanh, làm công ty, cho thuê,.. Sổ hồng chính chủ, pháp lý chuẩn. Liên hệ anh Võ: 0909 100 817. Không tiếp trung gian.", "Bán Nhà mặt phố", "Tân Bình", "12 tỷ", ["Mã tin: 271234", "Ngày đăng: 17:00 01/07/2023"], ["Diện tích: 56 m2", "Phòng ngủ: 4 PN", "Phòng WC: 4 WC", "Địa chỉ: Bàu Cát 1, P.14, Tân Bình"]], "19": ["https://batdongsan.vn/nha-phu-nhuan-hem-oto-thong-52m2-1-tret-3lau-4-pngu-8x-ty-r271233", "Nhà Phú Nhuận - HẺM ÔTÔ Thông - 52M2 - 1 Trệt 3Lầu - 4 P.Ngủ - 8.x Tỷ", "- Dt: 4x13 (52m2) sổ vuông vức\n- Nhà 1sẹt Lê Văn Sỹ thuận tiện kinh doanh\n- Nhà 1trệt 3lầu, 4 phòng ngủ \n- Hẻm xe hơi thông ra Trường Sa", "Bán Nhà riêng", "Phú Nhuận", "8.2 tỷ", ["Mã tin: 271233", "Ngày đăng: 17:07 01/07/2023"], ["Diện tích: 52 m2", "Phòng ngủ: 4 PN", "Phòng WC: 4 WC", "Địa chỉ: 5"]]}