{"0": ["https://batdongsan.vn/ban-nha-go-vap-nguyen-van-khoi-phuong-9-hxh-63m2-4-tang-chi-72-ty-r281671", "Bán nhà Gò Vấp, Nguyễn Văn Khối Phường 9, HXH 63m2 4 tầng chỉ 7.2 tỷ", "Gò Vấp", ["Mã tin: 281671", "Ngày đăng: 10:34 24/10/2023"], ["7.2 tỷ", "Diện tích: 63 m2", "Phòng ngủ: 4 PN", "Địa chỉ: Nguyễn Văn Khối"]], "1": ["https://batdongsan.vn/ban-nha-hem-xe-tai-thach-lam-tan-phu-66m-vuong-a4-3-tang-btct-chi-nhinh-4-ty-r281669", "BÁN NHÀ HẺM XE TẢI THẠCH LAM, TÂN PHÚ - 66M VUÔNG A4 - 3 TẦNG BTCT - CHỈ NHỈNH 4 TỶ.", "Tân Phú", ["Mã tin: 281669", "Ngày đăng: 11:26 24/10/2023"], ["4.9 tỷ", "Diện tích: 66 m2", "Phòng ngủ: 3 PN", "Địa chỉ: Thành phố Hồ Chí Minh"]], "2": ["https://batdongsan.vn/gap-ban-nha-bui-thi-xuan-54m2-4-tang-hxh-sat-mt-gia-chi-73-ty-r281657", "Gấp bán nhà Bùi Thị Xuân 54m2, 4 tầng, hxh, sát MT giá chỉ 7,3 tỷ.", "Tân Bình", ["Mã tin: 281657", "Ngày đăng: 12:20 24/10/2023"], ["7.3 tỷ", "Diện tích: 54 m2", "Phòng ngủ: 6 PN", "Phòng WC: 6 WC", "Địa chỉ: Bùi Thị Xuân P3 Quận Tân Bình"]], "3": ["https://batdongsan.vn/ban-nha-mat-tien-duong-lon-an-duong-vuong-phuong-an-lac-quan-binh-tan-r281656", "Bán nhà mặt tiền đường lớn An Dương Vương, Phường An Lạc, Quận Bình Tân", "Bình Tân", ["Mã tin: 281656", "Ngày đăng: 12:51 24/10/2023"], ["302.47 tỷ", "Diện tích: 840.2 m2", "Địa chỉ: so 324 An Dương Vương, Phường An Lạc, Quận Bình Tân"]], "4": ["https://batdongsan.vn/ban-nha-2-mat-tien-duong-lon-an-duong-vuong-va-duong-so-1-phuong-an-lac-quan-binh-tan-tp-hcm-r281655", "Bán nhà 2 mặt tiền đường lớn An Dương Vương và Đường số 1 Phường An Lạc, Quận Bình Tân, TP. HCM", "Bình Tân", ["Mã tin: 281655", "Ngày đăng: 12:56 24/10/2023"], ["430.47 tỷ", "Diện tích: 1229.92 m2", "Địa chỉ: Góc 2 mặt tiền đường lớn An Dương Vương và Đường số 1, Phường An Lạc, Quận Bình Tân."]], "5": ["https://batdongsan.vn/nha-dep-full-noi-that-don-vao-o-ngay-duong-dinh-tien-hoang-giap-q1-chi-465-ty-r281652", "Nhà Đẹp, Full nội thất, dọn vào ở ngay, đường Đinh Tiên Hoàng, giáp Q.1, chỉ 4,65 tỷ", "Bình Thạnh", ["Mã tin: 281652", "Ngày đăng: 13:30 24/10/2023"], ["4.65 tỷ", "Diện tích: 28 m2", "Phòng ngủ: 2 PN", "Phòng WC: 3 WC"]], "6": ["https://batdongsan.vn/ban-nha-truong-chinh-tan-binh-hem-xe-tai-gia-82-ty-r281650", "BÁN NHÀ TRƯỜNG CHINH TÂN BÌNH, HẼM XE TẢI GIÁ 8.2 TỶ", "Tân Bình", ["Mã tin: 281650", "Ngày đăng: 13:32 24/10/2023"], ["8.2 tỷ", "Diện tích: 80 m2", "Phòng ngủ: 4 PN"]], "7": ["https://batdongsan.vn/ban-nha-mat-tien-duong-1a-gan-sieu-thi-aeon-r281648", "-\tBán nhà mặt tiền đường 1A gần siêu thị Aeon", "Bình Tân", ["Mã tin: 281648", "Ngày đăng: 13:45 24/10/2023"], ["11.3 tỷ", "Diện tích: 84 m2"]], "8": ["https://batdongsan.vn/ban-nha-94m2-truong-chinh-tan-binh-hem-xe-hoi-gia-87-ty-r281647", "BÁN NHÀ 94M2 TRƯỜNG CHINH TÂN BÌNH, HẼM XE HƠI GIÁ 8.7 TỶ", "Tân Bình", ["Mã tin: 281647", "Ngày đăng: 13:47 24/10/2023"], ["8.7 tỷ", "Diện tích: 94 m2", "Phòng ngủ: 9 PN", "Phòng WC: 6 WC"]], "9": ["https://batdongsan.vn/ban-nha-hem-duong-ten-lua-sat-aeon-r281644", "-\tBán nhà hẻm đường Tên lửa, Sát AEON", "Bình Tân", ["Mã tin: 281644", "Ngày đăng: 13:58 24/10/2023"], ["2.7 tỷ", "Diện tích: 58 m2"]], "10": ["https://batdongsan.vn/ban-nha-hem-duong-ten-lua-sat-aeon-r281643", "-\tBán nhà hẻm đường Tên lửa, Sát AEON", "Bình Tân", ["Mã tin: 281643", "Ngày đăng: 13:58 24/10/2023"], ["2.7 tỷ", "Diện tích: 58 m2"]], "11": ["https://batdongsan.vn/le-van-quoi-56m2-hem-xe-hoi-tuong-lai-ra-mat-tien-37-ty-0948362610-r281639", "LÊ VĂN QUỚI 56M2 HẺM XE HƠI TƯƠNG LAI RA MẶT TIỀN 3,7 TỶ, 0948362610", "Bình Tân", ["Mã tin: 281639", "Ngày đăng: 14:00 24/10/2023"], ["3.7 tỷ", "Diện tích: 56 m2", "Địa chỉ: Lê Văn Quới, Bình Hưng Hòa A, Bình Tân"]], "12": ["https://batdongsan.vn/nha-4-tang-tien-o-kinh-doanh-gan-aeon-tan-phu-285-ty-r281636", "Nhà 4 tầng tiện ở kinh doanh, gần Aeon Tân Phú, 2.85 tỷ", "Tân Phú", ["Mã tin: 281636", "Ngày đăng: 14:01 24/10/2023"], ["2.85 tỷ", "Diện tích: 35 m2", "Phòng ngủ: 2 PN", "Phòng WC: 2 WC", "Địa chỉ: Tân Kỳ Tân Quý, Sơn Kỳ, Tân Phú"]], "13": ["https://batdongsan.vn/ban-nha-mat-tien-duong-so-3-doi-dien-truong-hoc-r281633", "Bán nhà mặt tiền đường số 3 đối diện trường học", "Bình Tân", ["Mã tin: 281633", "Ngày đăng: 14:11 24/10/2023"], ["15 tỷ", "Diện tích: 80 m2"]], "14": ["https://batdongsan.vn/ban-nha-mat-tien-duong-so-3-doi-dien-truong-hoc-r281632", "Bán nhà mặt tiền đường số 3 đối diện trường học", "Bình Tân", ["Mã tin: 281632", "Ngày đăng: 14:11 24/10/2023"], ["15 tỷ", "Diện tích: 80 m2"]], "15": ["https://batdongsan.vn/nha-pho-goc-mat-tien-duong-so-1-va-duong-so-2-phuong-an-lac-quan-binh-tan-r281628", "Nhà phố góc mặt tiền Đường số 1 và Đường số 2 Phường An Lạc, Quận Bình Tân", "Bình Tân", ["Mã tin: 281628", "Ngày đăng: 14:28 24/10/2023"], ["386.08 tỷ", "Diện tích: 1016 m2", "Địa chỉ: Căn góc 2 mặt tiền số 12 Đường số 1 và Đường số 2, Phường An Lạc, Quận Bình Tân."]], "16": ["https://batdongsan.vn/ban-can-goc-2-mt-mat-tien-duong-so-2-khu-ten-lua-r281624", "Bán căn góc 2 mt  mặt tiền đường số 2 khu Tên Lửa", "Bình Tân", ["Mã tin: 281624", "Ngày đăng: 14:37 24/10/2023"], ["12.7 tỷ", "Diện tích: 100 m2"]], "17": ["https://batdongsan.vn/nhung-loai-cua-go-chong-chay-duoc-su-dung-nhieu-nhat-r281622", "Những loại cửa gỗ chống cháy được sử dụng nhiều nhất", "Thủ Đức", ["Mã tin: 281622", "Ngày đăng: 14:40 24/10/2023"], ["Thỏa thuận"]], "18": ["https://batdongsan.vn/ban-nha-1-lau-hem-xe-hoi-gan-cho-nguyen-thi-tan-phuong-2-quan-8-r281619", "Bán nhà 1 lầu hẻm xe hơi gần chợ Nguyễn Thị Tần Phường 2 Quận 8", "Quận 8", ["Mã tin: 281619", "Ngày đăng: 15:24 24/10/2023"], ["6.8 tỷ", "Diện tích: 46 m2"]], "19": ["https://batdongsan.vn/ban-nha-moi-1-lau-3x11m-hem-154-duong-au-duong-lan-p3-quan-8-r281618", "Bán nhà mới 1 lầu 3x11m hẻm 154 đường Âu Dương Lân P.3 Quận 8", "Quận 8", ["Mã tin: 281618", "Ngày đăng: 15:40 24/10/2023"], ["3.68 tỷ", "Diện tích: 33 m2"]]}