{"0": ["https://batdongsan.vn/ban-nha-hem-xe-tai-duong-thach-lam-phu-thanh-tan-phu-r283603", "Bán nhà hẻm xe tải đường Thạch Lam Phú Thạnh Tân Phú", "Tân Phú", ["Mã tin: 283603", "Ngày đăng: 09:02 22/11/2023"], ["6.85 tỷ", "Diện tích: 72 m2", "Phòng ngủ: 3 PN", "Phòng WC: 3 WC", "Địa chỉ: Thạch Lam Phú Thạnh Tân Phú, Chọn dự án"]], "1": ["https://batdongsan.vn/ban-nha-go-vap-duong-so-4-phuong-16-73m2-4-tang-chi-9-ty-r283598", "Bán nhà Gò Vấp Đường Số 4 Phường 16, 73m2, 4 tầng chỉ 9 tỷ", "Gò Vấp", ["Mã tin: 283598", "Ngày đăng: 09:30 22/11/2023"], ["9 tỷ", "Diện tích: 73 m2", "Phòng ngủ: 5 PN", "Phòng WC: 6 WC", "Hướng nhà: Bắc", "Địa chỉ: Đường Số 4"]], "2": ["https://batdongsan.vn/ban-nha-mat-tien-duong-cao-duc-lan-16-ty-4x20m-an-phu-q2-vi-tri-dep-r283595", "Bán nhà mặt tiền đường Cao Đức Lân, 16 tỷ, 4x20m, An Phú, Q2, vị trí đẹp", "Quận 2", ["Mã tin: 283595", "Ngày đăng: 09:42 22/11/2023"], ["16 tỷ", "Diện tích: 80 m2", "Phòng ngủ: 4 PN", "Phòng WC: 5 WC", "Địa chỉ: Quận 2, Hồ Chí Minh"]], "3": ["https://batdongsan.vn/sat-duong-oto-6m-no-trang-long-binh-thanh-2-tang-btct-60m2-4x-ty-r283594", "SÁT ĐƯỜNG ÔTÔ 6M NƠ TRANG LONG, BÌNH THẠNH, 2 TẦNG BTCT, 60M2, 4.x TỶ", "Bình Thạnh", ["Mã tin: 283594", "Ngày đăng: 09:49 22/11/2023"], ["4.9 tỷ", "Diện tích: 60 m2", "Phòng ngủ: 3 PN", "Phòng WC: 3 WC"]], "4": ["https://batdongsan.vn/ban-gap-nha-phuong-binh-chieu-56m2-2-tang-duong-ngo-chi-quoc-r283582", "BÁN GẤP NHÀ PHƯỜNG BÌNH CHIỂU - 56m2 - 2 TẦNG - ĐƯỜNG NGÔ CHÍ QUỐC", "Thủ Đức", ["Mã tin: 283582", "Ngày đăng: 10:58 22/11/2023"], ["3.3 tỷ", "Diện tích: 56 m2", "Phòng ngủ: 2 PN", "Phòng WC: 2 WC", "Địa chỉ: Hẻm 80 Ngô Chí Quốc, Phường Bình Chiểu TP.Thủ Đức"]], "5": ["https://batdongsan.vn/cua-go-cong-nghiep-mdf-laminate-cao-cap-tai-quan-1-r283579", "Cửa gỗ công nghiệp MDF laminate cao cấp tại Quận 1", "Quận 1", ["Mã tin: 283579", "Ngày đăng: 11:08 22/11/2023"], ["Thỏa thuận"]], "6": ["https://batdongsan.vn/can-ban-gap-nha-mat-tien-duong-so-39-gia-re-chi-7-ty-850-r283574", "cần bán gấp nhà mặt tiền đường số 39 giá rẻ chỉ 7 tỷ 850", "Quận 7", ["Mã tin: 283574", "Ngày đăng: 13:08 22/11/2023"], ["7.85 tỷ", "Diện tích: 60 m2", "Phòng ngủ: 1 PN", "Phòng WC: 1 WC"]], "7": ["https://batdongsan.vn/nha-re-bat-ngo-quan-4-hem-1-sec-42m2-hai-tang-gia-chi-33-ty-r283572", "NHÀ RẺ BẤT NGỜ, QUẬN 4 HẼM 1 SẸC, 42m2 HAI TẦNG, GIÁ CHỈ 3,3 TỶ", "Quận 4", ["Mã tin: 283572", "Ngày đăng: 13:58 22/11/2023"], ["3.3 tỷ", "Diện tích: 42 m2", "Phòng ngủ: 3 PN", "Phòng WC: 1 WC", "Địa chỉ: Đường Tôn Thất Thuyết, Phường 3, Quận 4, TP. HCM"]], "8": ["https://batdongsan.vn/discover-the-power-of-facebook-advertising-r283571", "Discover the Power of Facebook Advertising", "Bình Chánh", ["Mã tin: 283571", "Ngày đăng: 14:03 22/11/2023"], ["12 triệu", "Diện tích: 200 m2", "Phòng ngủ: 12 PN", "Phòng WC: 12 WC", "Hướng nhà: Nam", "Hướng ban công: Nam", "Địa chỉ: quận 2"]], "9": ["https://batdongsan.vn/discover-the-power-of-facebook-advertising-r283570", "Discover the Power of Facebook Advertising", "Bình Chánh", ["Mã tin: 283570", "Ngày đăng: 14:03 22/11/2023"], ["12 triệu", "Diện tích: 200 m2", "Phòng ngủ: 12 PN", "Phòng WC: 12 WC", "Hướng nhà: Nam", "Hướng ban công: Nam", "Địa chỉ: quận 2"]], "10": ["https://batdongsan.vn/ngay-khu-pho-am-thuc-phan-xich-long-hem-xe-tai-tranh-can-ban-nha-7143-nguyen-cong-hoan-r283558", "Ngay Khu phố ẩm thực Phan Xích Long, hẻm xe tải tránh, cần bán nhà 71/43 Nguyễn Công Hoan", "Phú Nhuận", ["Mã tin: 283558", "Ngày đăng: 14:56 22/11/2023"], ["Thỏa thuận", "Diện tích: 62 m2", "Phòng ngủ: 3 PN", "Phòng WC: 4 WC", "Hướng nhà: Tây-Nam", "Địa chỉ: 71/43"]], "11": ["https://batdongsan.vn/nha-ngay-hoang-van-thu-lang-cha-ca-cong-nhan-du-30m2-no-hau-3-ty-r283555", "Nhà ngay Hoàng Văn Thụ, Lăng Cha Cả, công nhận đủ 30m2, nở hậu, 3 tỷ", "Tân Bình", ["Mã tin: 283555", "Ngày đăng: 15:33 22/11/2023"], ["3 tỷ", "Diện tích: 30 m2", "Phòng ngủ: 2 PN", "Phòng WC: 2 WC", "Địa chỉ: Thành phố Hồ Chí Minh"]], "12": ["https://batdongsan.vn/ban-nha-3-lau-mat-tien-duong-vo-liem-son-phuong-4-quan-8-r283553", "Bán nhà 3 lầu mặt tiền đường Võ Liêm Sơn Phường 4 Quận 8", "Quận 8", ["Mã tin: 283553", "Ngày đăng: 15:38 22/11/2023"], ["13 tỷ", "Diện tích: 80 m2"]], "13": ["https://batdongsan.vn/ban-chdv-4-lau-goc-2-mat-hem-gan-duong-pham-hung-phuong-4-quan-8-r283552", "Bán CHDV 4 lầu góc 2 mặt hẻm gần đường Phạm Hùng Phường 4 Quận 8", "Quận 8", ["Mã tin: 283552", "Ngày đăng: 15:45 22/11/2023"], ["10.5 tỷ", "Diện tích: 100 m2"]], "14": ["https://batdongsan.vn/ban-nha-quan-6-nha-nho-3-tang-dtsd-36m-khong-quy-hoach-nhinh-1ty-r283543", "Bán Nhà Quận 6 - Nhà Nhỏ 3 Tầng - DTSD 36M - Không Quy Hoạch - Nhỉnh 1Tỷ", "Quận 6", ["Mã tin: 283543", "Ngày đăng: 18:32 22/11/2023"], ["1.62 tỷ", "Diện tích: 12 m2", "Địa chỉ: Thành phố Hồ Chí Minh"]], "15": ["https://batdongsan.vn/sieu-pham-nha-dep-lung-linh-2-tang-trung-tam-tan-binh-r283539", "SIÊU PHẨM - NHÀ ĐẸP LUNG LINH 2 TẦNG - TRUNG TÂM TÂN BÌNH", "Tân Bình", ["Mã tin: 283539", "Ngày đăng: 21:43 22/11/2023"], ["5.1 tỷ", "Diện tích: 77 m2", "Phòng ngủ: 3 PN", "Phòng WC: 4 WC", "Địa chỉ: Thành phố Hồ Chí Minh"]], "16": ["https://batdongsan.vn/sieu-pham-nha-dep-lung-linh-2-tang-trung-tam-tan-binh-r283538", "SIÊU PHẨM - NHÀ ĐẸP LUNG LINH 2 TẦNG - TRUNG TÂM TÂN BÌNH", "Tân Bình", ["Mã tin: 283538", "Ngày đăng: 21:43 22/11/2023"], ["5.1 tỷ", "Diện tích: 77 m2", "Phòng ngủ: 3 PN", "Phòng WC: 4 WC", "Địa chỉ: Thành phố Hồ Chí Minh"]], "17": ["https://batdongsan.vn/anh-hai-gui-e-ban-can-nha-2-tang-60m2-sat-mat-tien-quan-binh-tan-chi-2x-ty-xiu-r283537", "???? Anh Hai gửi E Bán Căn Nhà - 2 Tầng - 60m2 - Sát Mặt Tiền - Quận Bình Tân - Chỉ 2.X Tỷ xíu", "Bình Tân", ["Mã tin: 283537", "Ngày đăng: 22:00 22/11/2023"], ["2.7 tỷ", "Diện tích: 60 m2"]], "18": ["https://batdongsan.vn/ban-gap-nha-hxh-tranh-99-ty-42mx15m-ngay-cho-do-dac-so-vuong-vuc-r283531", "Bán gấp nhà HXH tránh 9.9 tỷ, 4.2mx15m, ngay chợ đo đạc, sổ vuông vức", "Quận 2", ["Mã tin: 283531", "Ngày đăng: 08:31 23/11/2023"], ["9.9 tỷ", "Diện tích: 61 m2", "Phòng ngủ: 2 PN", "Phòng WC: 1 WC", "Địa chỉ: Quận 2, Hồ Chí Minh"]], "19": ["https://batdongsan.vn/ban-nha-mat-tien-tran-nao-kinh-doanh-sam-uat-q2-55x20m-30-ty-vi-tri-dep-r283527", "Bán nhà mặt tiền Trần Não, Kinh doanh sầm uất Q2, 5.5x20m, 30 tỷ, vị trí đẹp", "Quận 2", ["Mã tin: 283527", "Ngày đăng: 08:58 23/11/2023"], ["30 tỷ", "Diện tích: 144 m2", "Phòng ngủ: 1 PN", "Phòng WC: 1 WC", "Địa chỉ: Quận 2, Hồ Chí Minh"]]}